README.rst
setup.py
x100idgen.py
x100idgen.egg-info/PKG-INFO
x100idgen.egg-info/SOURCES.txt
x100idgen.egg-info/dependency_links.txt
x100idgen.egg-info/top_level.txt