Metadata-Version: 1.1
Name: x100idgen
Version: 0.1.9
Summary: Id generator require no centralized authority
Home-page: https://github.com/chengang/x100idgen
Author: Chen Gang
Author-email: yikuyiku.com@gmail.com
License: MIT
Keywords: uuid idgen id IdGenerator x100
Platform: UNKNOWN
Classifier: Development Status :: 4 - Beta
Classifier: Intended Audience :: Developers
Classifier: Topic :: Utilities
Classifier: License :: OSI Approved :: MIT License
Classifier: Programming Language :: Python :: 3.3
Classifier: Programming Language :: Python :: 3.4
Classifier: Programming Language :: Python :: 3 :: Only
